{"version": 0.6, "generator": "Overpass API 0.7.61.5 4133829e", "osm3s": {"timestamp_osm_base": "2024-03-13T22:45:43Z", "copyright": "The data included in this document is from www.openstreetmap.org. The data is made available under ODbL."}, "elements": [{"type": "node", "id": 1185811835, "lat": 41.8603092, "lon": 43.4213854, "tags": {"amenity": "pharmacy", "healthcare": "pharmacy", "source": "JumpStart International"}}, {"type": "node", "id": 1185812078, "lat": 41.8401583, "lon": 43.3786092, "tags": {"amenity": "pharmacy", "healthcare": "pharmacy", "source": "JumpStart International"}}, {"type": "node", "id": 1185812269, "lat": 41.8408847, "lon": 43.3838404, "tags": {"amenity": "pharmacy", "healthcare": "pharmacy", "source": "JumpStart International"}}, {"type": "node", "id": 1185812295, "lat": 41.8417502, "lon": 43.3800205, "tags": {"amenity": "pharmacy", "brand": "\u10d0\u10d5\u10d4\u10e0\u10e1\u10d8", "brand:en": "Aversi", "brand:ka": "\u10d0\u10d5\u10d4\u10e0\u10e1\u10d8", "brand:ru": "\u0410\u0432\u0435\u0440\u0441\u0438", "brand:wikidata": "Q55653978", "contact:facebook": "https://facebook.com/AversiPharma", "contact:instagram": "https://instagram.com/aversipharma", "contact:linkedin": "https://linkedin.com/company/aversi-pharma", "contact:website": "https://www.aversi.ge", "contact:youtube": "https://youtube.com/user/AversiPharma", "healthcare": "pharmacy", "name": "\u10d0\u10d5\u10d4\u10e0\u10e1\u10d8", "name:en": "Aversi", "name:ka": "\u10d0\u10d5\u10d4\u10e0\u10e1\u10d8", "name:ru": "\u0410\u0432\u0435\u0440\u0441\u0438", "operator:wikidata": "Q55653978", "payment:american_express": "yes", "payment:contactless": "yes", "payment:credit_cards": "yes", "payment:debit_cards": "yes", "payment:mastercard": "yes", "payment:visa": "yes", "source": "JumpStart International"}}, {"type": "node", "id": 1185812453, "lat": 41.8387469, "lon": 43.3783298, "tags": {"amenity": "pharmacy", "healthcare": "pharmacy", "source": "JumpStart International"}}, {"type": "node", "id": 1185812586, "lat": 41.8395026, "lon": 43.3786409, "tags": {"amenity": "pharmacy", "brand": "\u10de\u10e1\u10de", "brand:en": "PSP", "brand:ka": "\u10de\u10e1\u10de", "brand:wikidata": "Q115970964", "contact:email": "online@psp.ge", "contact:facebook": "https://facebook.com/psp.ge", "contact:instagram": "https://instagram.com/psp_pharmacy", "contact:website": "https://psp.ge", "contact:youtube": "https://youtube.com/user/PSPN1TV", "healthcare": "pharmacy", "name": "\u10de\u10e1\u10de", "name:en": "PSP", "name:ka": "\u10de\u10e1\u10de", "operator:wikidata": "Q115970964", "payment:alipay": "no", "payment:american_express": "yes", "payment:apple_pay": "yes", "payment:cash": "yes", "payment:contactless": "yes", "payment:credit_cards": "yes", "payment:debit_cards": "yes", "payment:diners_club": "yes", "payment:discover_card": "yes", "payment:google_pay": "yes", "payment:jcb": "yes", "payment:mastercard": "yes", "payment:mir": "no", "payment:samsung_pay": "no", "payment:unionpay": "yes", "payment:visa": "yes", "source": "JumpStart International"}}, {"type": "node", "id": 4022151186, "lat": 41.750098, "lon": 43.5282602}, {"type": "node", "id": 6297990212, "lat": 41.8392106, "lon": 43.378679, "tags": {"amenity": "pharmacy", "brand": "\u10e4\u10d0\u10e0\u10db\u10d0\u10d3\u10d4\u10de\u10dd", "brand:en": "Pharmadepot", "brand:ru": "\u0424\u0430\u0440\u043c\u0430\u0434\u0435\u043f\u043e", "brand:wikidata": "Q115971332", "contact:facebook": "https://facebook.com/Pharmadepot", "healthcare": "pharmacy", "name": "\u10e4\u10d0\u10e0\u10db\u10d0\u10d3\u10d4\u10de\u10dd", "name:en": "Pharmadepot", "name:ka": "\u10e4\u10d0\u10e0\u10db\u10d0\u10d3\u10d4\u10de\u10dd", "name:ru": "\u0424\u0430\u0440\u043c\u0430\u0434\u0435\u043f\u043e\u0442", "operator:wikidata": "Q115971332", "payment:alipay": "no", "payment:american_express": "yes", "payment:apple_pay": "yes", "payment:cash": "yes", "payment:contactless": "yes", "payment:credit_cards": "yes", "payment:debit_cards": "yes", "payment:diners_club": "yes", "payment:discover_card": "yes", "payment:google_pay": "yes", "payment:jcb": "yes", "payment:mastercard": "yes", "payment:mir": "no", "payment:samsung_pay": "no", "payment:unionpay": "yes", "payment:visa": "yes"}}, {"type": "node", "id": 6765770389, "lat": 41.7492086, "lon": 43.5291504, "tags": {"addr:city": "Bakuriani", "amenity": "pharmacy", "dispensing": "yes", "healthcare": "pharmacy"}}, {"type": "node", "id": 6765784404, "lat": 41.7501419, "lon": 43.5284375}, {"type": "node", "id": 6765784405, "lat": 41.7500749, "lon": 43.5284673}, {"type": "node", "id": 6765784406, "lat": 41.7500311, "lon": 43.5282899}, {"type": "node", "id": 6765784408, "lat": 41.7507751, "lon": 43.5280175, "tags": {"addr:city": "Bakuriani", "amenity": "pharmacy", "brand": "36,6", "brand:wikidata": "Q226889", "brand:wikipedia": "ru:36,6 (\u0430\u043f\u0442\u0435\u0447\u043d\u0430\u044f \u0441\u0435\u0442\u044c)", "dispensing": "yes", "healthcare": "pharmacy", "name": "36,6"}}, {"type": "node", "id": 6765784413, "lat": 41.7507068, "lon": 43.5277512, "tags": {"addr:city": "Bakuriani", "amenity": "pharmacy", "brand": "\u10e4\u10d0\u10e0\u10db\u10d0\u10d3\u10d4\u10de\u10dd", "brand:en": "Pharmadepot", "brand:ru": "\u0424\u0430\u0440\u043c\u0430\u0434\u0435\u043f\u043e\u0442", "contact:facebook": "https://facebook.com/Pharmadepot", "dispensing": "yes", "healthcare": "pharmacy", "name": "\u10e4\u10d0\u10e0\u10db\u10d0\u10d3\u10d4\u10de\u10dd", "name:en": "Pharmadepot", "name:ka": "\u10e4\u10d0\u10e0\u10db\u10d0\u10d3\u10d4\u10de\u10dd", "name:ru": "\u0424\u0430\u0440\u043c\u0430\u0434\u0435\u043f\u043e", "name:uk": "\u0424\u0430\u0440\u043c\u0430\u0434\u0435\u043f\u043e", "operator": "Pharmadepot", "operator:wikidata": "Q115971332", "payment:american_express": "yes", "payment:contactless": "yes", "payment:credit_cards": "yes", "payment:debit_cards": "yes", "payment:mastercard": "yes", "payment:visa": "yes"}}, {"type": "node", "id": 6765784414, "lat": 41.7506734, "lon": 43.5276201, "tags": {"addr:city": "Bakuriani", "amenity": "pharmacy", "dispensing": "yes", "healthcare": "pharmacy", "name": "PSP", "name:ka": "\u10de\u10e1\u10de", "operator": "PSP"}}, {"type": "node", "id": 11654605369, "lat": 41.7312767, "lon": 43.5297581, "tags": {"amenity": "pharmacy", "internet_access": "wlan", "name:en": "Apotheke", "opening_hours": "24/7"}}, {"type": "node", "id": 11704718272, "lat": 41.8393915, "lon": 43.3789173, "tags": {"amenity": "pharmacy", "brand": "\u10d8\u10db\u10de\u10d4\u10e5\u10e1\u10d8", "brand:en": "Impex", "brand:ka": "\u10d8\u10db\u10de\u10d4\u10e5\u10e1\u10d8", "brand:ru": "\u0418\u043c\u043f\u0435\u043a\u0441", "contact:email": "office@myimpex.ge", "contact:facebook": "https://facebook.com/ImpexPharmacy", "contact:instagram": "https://instagram.com/impexpharmacy", "contact:linkedin": "https://linkedin.com/company/impexpharm", "contact:phone": "+995 32 231 31 00", "healthcare": "pharmacy", "name": "\u10d8\u10db\u10de\u10d4\u10e5\u10e1\u10d8", "name:en": "Impex", "name:ka": "\u10d8\u10db\u10de\u10d4\u10e5\u10e1\u10d8", "name:ru": "\u0418\u043c\u043f\u0435\u043a\u0441", "payment:alipay": "no", "payment:american_express": "yes", "payment:apple_pay": "yes", "payment:cash": "yes", "payment:contactless": "yes", "payment:credit_cards": "yes", "payment:debit_cards": "yes", "payment:diners_club": "yes", "payment:discover_card": "yes", "payment:google_pay": "yes", "payment:jcb": "yes", "payment:mastercard": "yes", "payment:mir": "no", "payment:samsung_pay": "no", "payment:unionpay": "yes", "payment:visa": "yes"}}, {"type": "way", "id": 721101449, "nodes": [4022151186, 6765784404, 6765784405, 6765784406, 4022151186], "tags": {"addr:city": "Bakuriani", "amenity": "pharmacy", "brand": "\u10d0\u10d5\u10d4\u10e0\u10e1\u10d8", "brand:en": "Aversi", "brand:ru": "\u0410\u0432\u0435\u0440\u0441\u0438", "brand:wikidata": "Q55653978", "building": "yes", "contact:facebook": "https://facebook.com/AversiPharma", "contact:instagram": "https://instagram.com/aversipharma", "contact:linkedin": "https://linkedin.com/company/aversi-pharma", "contact:website": "https://www.aversi.ge", "contact:youtube": "https://youtube.com/user/AversiPharma", "dispensing": "yes", "healthcare": "pharmacy", "name": "\u10d0\u10d5\u10d4\u10e0\u10e1\u10d8", "name:en": "Aversi", "name:ka": "\u10d0\u10d5\u10d4\u10e0\u10e1\u10d8", "name:ru": "\u0410\u0432\u0435\u0440\u0441\u0438", "operator": "Aversi", "operator:wikidata": "Q55653978", "payment:american_express": "yes", "payment:contactless": "yes", "payment:credit_cards": "yes", "payment:debit_cards": "yes", "payment:mastercard": "yes", "payment:visa": "yes"}}]}