{"version": 0.6, "generator": "Overpass API 0.7.61.5 4133829e", "osm3s": {"timestamp_osm_base": "2024-03-13T23:10:52Z", "copyright": "The data included in this document is from www.openstreetmap.org. The data is made available under ODbL."}, "elements": [{"type": "node", "id": 1148682127, "lat": 41.9404479, "lon": 42.7560259, "tags": {"amenity": "restaurant", "name": "\u10ef\u10d0\u10e0\u10d2\u10d5\u10d0\u10da\u10d8 (Jargvali)", "name:en": "Jargvali", "name:ka": "\u10ef\u10d0\u10e0\u10d2\u10d5\u10d0\u10da\u10d8", "source": "JumpStart International"}}, {"type": "node", "id": 1157550453, "lat": 42.0724634, "lon": 42.8237218, "tags": {"amenity": "cafe", "name": "\u10d0\u10db\u10dd\u10e0\u10d4", "name:en": "Amore", "name:ka": "\u10d0\u10db\u10dd\u10e0\u10d4", "name:ru": "Amore", "source": "JumpStart International"}}, {"type": "node", "id": 1157550485, "lat": 42.0675379, "lon": 42.8258989, "tags": {"amenity": "restaurant", "name": "\u10e1\u10d0\u10d1\u10d0\u10dc\u10d9\u10d4\u10e2\u10dd", "name:en": "Sabanketo", "name:ka": "\u10e1\u10d0\u10d1\u10d0\u10dc\u10d9\u10d4\u10e2\u10dd", "name:ru": "\u0421\u0430\u0431\u0430\u043d\u043a\u0435\u0442\u043e", "source": "JumpStart International"}}, {"type": "node", "id": 1157550488, "lat": 42.0670794, "lon": 42.8243341, "tags": {"amenity": "cafe", "name": "\u10e1\u10d0\u10d7\u10dc\u10dd\u10d4\u10d1\u10d8\u10e1 \u10e1\u10d0\u10ee\u10da\u10d8 \u10d9\u10d0\u10d7\u10d0\u10e0\u10d6\u10d8\u10e1\u10d8", "name:en": "Katarzisi Charity Dining Hall", "name:ka": "\u10e1\u10d0\u10d7\u10dc\u10dd\u10d4\u10d1\u10d8\u10e1 \u10e1\u10d0\u10ee\u10da\u10d8 \u10d9\u10d0\u10d7\u10d0\u10e0\u10d6\u10d8\u10e1\u10d8", "source": "JumpStart International"}}, {"type": "node", "id": 1157550506, "lat": 42.0147497, "lon": 42.833, "tags": {"amenity": "restaurant", "name": "\u10ec\u10e7\u10d0\u10da\u10d7\u10d0\u10e8\u10e3\u10d0", "name:en": "Tskaltashua", "name:ka": "\u10ec\u10e7\u10d0\u10da\u10d7\u10d0\u10e8\u10e3\u10d0", "name:ru": "\u0426\u043a\u0430\u043b\u0442\u0430\u0448\u0443\u0430", "source": "JumpStart International"}}, {"type": "node", "id": 1157550508, "lat": 42.0797792, "lon": 42.822938, "tags": {"amenity": "cafe", "name": "\u10d9\u10d8\u10ee\u10e3\u10e0\u10d0", "name:en": "Kikhura", "name:ka": "\u10d9\u10d8\u10ee\u10e3\u10e0\u10d0", "name:ru": "\u041a\u0438\u0445\u0443\u0440\u0430", "source": "JumpStart International"}}, {"type": "node", "id": 1157550542, "lat": 42.0681889, "lon": 42.8249091, "tags": {"amenity": "cafe", "source": "JumpStart International"}}, {"type": "node", "id": 1158876183, "lat": 42.2908007, "lon": 43.2867533, "tags": {"amenity": "cafe", "source": "JumpStart International"}}, {"type": "node", "id": 1158876196, "lat": 42.2913661, "lon": 43.2877109, "tags": {"amenity": "cafe", "source": "JumpStart International"}}, {"type": "node", "id": 1158876206, "lat": 42.2959298, "lon": 43.2768915, "tags": {"amenity": "cafe", "name": "\u10d3\u10d0\u10d5\u10d8\u10e2\u10d8 (Daviti)", "name:en": "Daviti", "name:ka": "\u10d3\u10d0\u10d5\u10d8\u10e2\u10d8", "source": "JumpStart International"}}, {"type": "node", "id": 1158876278, "lat": 42.2905658, "lon": 43.2850977, "tags": {"amenity": "cafe", "name": "\u10d1\u10d4\u10dc\u10d4\u10e4\u10d8\u10e2\u10d8 (Benefit)", "name:en": "Benefit", "name:ka": "\u10d1\u10d4\u10dc\u10d4\u10e4\u10d8\u10e2\u10d8", "source": "JumpStart International"}}, {"type": "node", "id": 1158876502, "lat": 42.2905102, "lon": 43.2850719, "tags": {"amenity": "restaurant", "name": "\u10d9\u10d5\u10d8\u10e0\u10d8\u10da\u10d0", "name:en": "Kvirila", "name:ka": "\u10d9\u10d5\u10d8\u10e0\u10d8\u10da\u10d0", "name:ru": "\u041a\u0432\u0438\u0440\u0438\u043b\u0430", "source": "JumpStart International"}}, {"type": "node", "id": 1158876918, "lat": 42.2908573, "lon": 43.2846709, "tags": {"amenity": "bar", "source": "JumpStart International"}}, {"type": "node", "id": 1159072109, "lat": 42.105374, "lon": 43.0346413, "tags": {"amenity": "cafe", "name": "\u10eb\u10d5\u10d4\u10da\u10d8 \u10d2\u10d4\u10db\u10dd (Dzveli Gemo)", "name:en": "Dzveli Gemo", "name:ka": "\u10eb\u10d5\u10d4\u10da\u10d8 \u10d2\u10d4\u10db\u10dd", "source": "JumpStart International"}}, {"type": "node", "id": 1159072140, "lat": 42.1032109, "lon": 43.2110516, "tags": {"amenity": "restaurant", "name": "\u10d6\u10e6\u10d0\u10de\u10d0\u10e0\u10d8", "name:en": "Zgapari", "name:ka": "\u10d6\u10e6\u10d0\u10de\u10d0\u10e0\u10d8", "source": "JumpStart International"}}, {"type": "node", "id": 1159072175, "lat": 42.1328203, "lon": 42.9841723, "tags": {"amenity": "restaurant", "check_date": "2023-09-30", "source": "JumpStart International"}}, {"type": "node", "id": 1159072210, "lat": 42.0141505, "lon": 43.2052186, "tags": {"amenity": "cafe", "source": "JumpStart International"}}, {"type": "node", "id": 1159072215, "lat": 42.0107483, "lon": 43.2088985, "tags": {"amenity": "cafe", "source": "JumpStart International"}}, {"type": "node", "id": 1159072246, "lat": 42.0130954, "lon": 43.2050618, "tags": {"amenity": "cafe", "source": "JumpStart International"}}, {"type": "node", "id": 1159072258, "lat": 42.1103218, "lon": 43.022589, "tags": {"amenity": "cafe", "name": "\u10ee\u10d0\u10ed\u10d0\u10de\u10e3\u10e0\u10d8 (Khatchapuri)", "name:en": "Khatchapuri", "name:ka": "\u10ee\u10d0\u10ed\u10d0\u10de\u10e3\u10e0\u10d8", "source": "JumpStart International"}}, {"type": "node", "id": 1159072364, "lat": 42.0113955, "lon": 43.2077537, "tags": {"amenity": "cafe", "source": "JumpStart International"}}, {"type": "node", "id": 1159072395, "lat": 42.1191087, "lon": 43.0126946, "tags": {"amenity": "cafe", "check_date": "2023-09-30", "name": "\u10e1\u10d0\u10d6\u10d0\u10dc\u10dd", "name:en": "Sazano", "name:ka": "\u10e1\u10d0\u10d6\u10d0\u10dc\u10dd", "source": "JumpStart International"}}, {"type": "node", "id": 1159072406, "lat": 42.1113874, "lon": 43.041251, "tags": {"addr:housenumber": "46", "addr:street": "\u10d7\u10d0\u10db\u10d0\u10e0\u10d8\u10e1 \u10e5\u10e3\u10e9\u10d0", "amenity": "cafe", "name": "\u10e1\u10d0\u10ee\u10d0\u10ed\u10d0\u10de\u10e3\u10e0\u10d4\u10d0", "name:en": "Cafe Richard", "opening_hours": "24/7", "source": "JumpStart International"}}, {"type": "node", "id": 1159072409, "lat": 42.0128303, "lon": 43.2054998, "tags": {"amenity": "cafe", "source": "JumpStart International"}}, {"type": "node", "id": 1159072414, "lat": 42.1140572, "lon": 43.0304318, "tags": {"amenity": "cafe", "name": "\u10e4\u10d0\u10e1\u10d0\u10dc\u10d0\u10e3\u10e0\u10d8 (Pasanauri)", "name:en": "Pasanauri", "name:ka": "\u10e4\u10d0\u10e1\u10d0\u10dc\u10d0\u10e3\u10e0\u10d8", "source": "JumpStart International"}}, {"type": "node", "id": 1159072444, "lat": 42.1141952, "lon": 43.0283835, "tags": {"amenity": "cafe", "name": "\u10d2\u10d4\u10db\u10dd (Gemo)", "name:en": "Gemo", "name:ka": "\u10d2\u10d4\u10db\u10dd", "source": "JumpStart International"}}, {"type": "node", "id": 1159072487, "lat": 42.1116127, "lon": 43.0397962, "tags": {"amenity": "cafe", "name": "\u10dd\u10ef\u10d0\u10ee\u10e3\u10e0\u10d8 \u10e1\u10d0\u10db\u10ee\u10d0\u10e0\u10d4\u10e3\u10da\u10dd (Ojakhuri Samzareulo)", "name:en": "Ojakhuri Samzareulo", "name:ka": "\u10dd\u10ef\u10d0\u10ee\u10e3\u10e0\u10d8 \u10e1\u10d0\u10db\u10ee\u10d0\u10e0\u10d4\u10e3\u10da\u10dd", "source": "JumpStart International"}}, {"type": "node", "id": 1159072490, "lat": 42.1071631, "lon": 43.0365189, "tags": {"amenity": "cafe", "source": "JumpStart International"}}, {"type": "node", "id": 1159072535, "lat": 42.1070271, "lon": 43.036277, "tags": {"amenity": "cafe", "name": "\u10e8\u10e3\u10d0 \u10e5\u10d0\u10da\u10d0\u10e5\u10e8\u10d8 (Shua Kalakshi)", "name:en": "Shua Kalakshi", "name:ka": "\u10e8\u10e3\u10d0 \u10e5\u10d0\u10da\u10d0\u10e5\u10e8\u10d8", "source": "JumpStart International"}}, {"type": "node", "id": 1159072543, "lat": 42.1080305, "lon": 43.0197928, "tags": {"amenity": "cafe", "source": "JumpStart International"}}, {"type": "node", "id": 1159072566, "lat": 42.10707, "lon": 43.0365598, "tags": {"amenity": "cafe", "name": "\u10d6\u10d5\u10d8\u10d0\u10d3\u10d8 (Zviadi)", "name:en": "Zviadi", "name:ka": "\u10d6\u10d5\u10d8\u10d0\u10d3\u10d8", "source": "JumpStart International"}}, {"type": "node", "id": 1159072567, "lat": 42.107092, "lon": 43.0319091, "tags": {"amenity": "cafe", "source": "JumpStart International"}}, {"type": "node", "id": 1159072610, "lat": 42.0900287, "lon": 43.1640705, "tags": {"amenity": "restaurant", "capacity": "50", "cuisine": "regional", "indoor_seating": "yes", "name": "\u10d8\u10db\u10d4\u10e0\u10d4\u10d7\u10d8 (Imereti)", "name:en": "Imereti", "name:ka": "\u10d8\u10db\u10d4\u10e0\u10d4\u10d7\u10d8", "opening_hours": "Mo-Su 10:00-22:00", "outdoor_seating": "yes", "source": "JumpStart International;local knowledge", "takeaway": "no"}}, {"type": "node", "id": 1159072660, "lat": 42.1054445, "lon": 43.0346257, "tags": {"amenity": "cafe", "name": "\u10e6\u10d5\u10d4\u10eb\u10d4\u10da\u10d8 (Gvezeli)", "name:en": "Gvezeli", "name:ka": "\u10e6\u10d5\u10d4\u10eb\u10d4\u10da\u10d8", "source": "JumpStart International"}}, {"type": "node", "id": 1163633061, "lat": 42.2154213, "lon": 42.7970447, "tags": {"amenity": "restaurant", "cuisine": "georgian", "name": "\u10ed\u10d8\u10e8\u10e3\u10e0\u10d0", "name:en": "Chishura", "name:ka": "\u10ed\u10d8\u10e8\u10e3\u10e0\u10d0", "source": "JumpStart International"}}, {"type": "node", "id": 1163633139, "lat": 42.1761539, "lon": 42.978787, "tags": {"amenity": "restaurant", "name": "\u10ee\u10d8\u10d3\u10d8\u10e1\u10d7\u10d0\u10d5\u10d8 (Khidistavi)", "name:en": "Khidistavi", "name:ka": "\u10ee\u10d8\u10d3\u10d8\u10e1\u10d7\u10d0\u10d5\u10d8", "source": "JumpStart International"}}, {"type": "node", "id": 1163633489, "lat": 42.2479334, "lon": 42.9554036, "tags": {"amenity": "restaurant", "source": "JumpStart International"}}, {"type": "node", "id": 1163633583, "lat": 42.179591, "lon": 42.977781, "tags": {"amenity": "cafe", "name": "\u10dd\u10d0\u10d6\u10d8\u10e1\u10d8 (Oasis)", "name:en": "Oasis", "name:ka": "\u10dd\u10d0\u10d6\u10d8\u10e1\u10d8", "source": "JumpStart International"}}, {"type": "node", "id": 1163633798, "lat": 42.1762569, "lon": 42.9771925, "tags": {"amenity": "restaurant", "source": "JumpStart International"}}, {"type": "node", "id": 1163633805, "lat": 42.2595739, "lon": 42.957326, "tags": {"amenity": "restaurant", "name": "\u10e8\u10d4\u10e0\u10e7\u10da\u10d8", "name:en": "Dzeruli", "name:ka": "\u10d1\u10d6\u10d4\u10d1\u10d8", "source": "JumpStart International"}}, {"type": "node", "id": 1164349480, "lat": 42.2871551, "lon": 42.7419284, "tags": {"amenity": "restaurant", "cuisine": "georgian", "name": "\u10e0\u10d4\u10e1\u10e2\u10dd\u10e0\u10d0\u10dc\u10d8 \u10db\u10dd\u10ec\u10d0\u10db\u10d4\u10d7\u10d0", "name:en": "Motsameta Restaurant", "name:ka": "\u10e0\u10d4\u10e1\u10e2\u10dd\u10e0\u10d0\u10dc\u10d8 \u10db\u10dd\u10ec\u10d0\u10db\u10d4\u10d7\u10d0", "name:ru": "\u041c\u043e\u0446\u0430\u043c\u0435\u0442\u0430", "source": "JumpStart International"}}, {"type": "node", "id": 1925504484, "lat": 42.101001, "lon": 43.217293, "tags": {"addr:city": "Ubisa", "addr:country": "GE", "amenity": "cafe", "name": "Malkhazi", "smoking": "yes", "wheelchair": "no", "wifi": "no"}}, {"type": "node", "id": 2690807571, "lat": 42.2046321, "lon": 42.8498492}, {"type": "node", "id": 2690807584, "lat": 42.2046083, "lon": 42.8496038}, {"type": "node", "id": 2690807603, "lat": 42.2044623, "lon": 42.8498793}, {"type": "node", "id": 2690807611, "lat": 42.2044385, "lon": 42.8496339}, {"type": "node", "id": 4207616643, "lat": 42.1141746, "lon": 43.0266611}, {"type": "node", "id": 4207616644, "lat": 42.1141357, "lon": 43.0265033}, {"type": "node", "id": 4207616645, "lat": 42.1145699, "lon": 43.0263086}, {"type": "node", "id": 4207616646, "lat": 42.1146132, "lon": 43.0264838}, {"type": "node", "id": 4207616647, "lat": 42.1144739, "lon": 43.0265463}, {"type": "node", "id": 4207616648, "lat": 42.1145507, "lon": 43.0268572}, {"type": "node", "id": 4207616649, "lat": 42.1144321, "lon": 43.0269104}, {"type": "node", "id": 4207616650, "lat": 42.114351, "lon": 43.026582}, {"type": "node", "id": 4228006354, "lat": 42.1093909, "lon": 43.0469331, "tags": {"amenity": "cafe", "name": "Cofe"}}, {"type": "node", "id": 4228006355, "lat": 42.1298457, "lon": 42.9930825, "tags": {"amenity": "restaurant", "name": "Megapolis"}}, {"type": "node", "id": 4347267591, "lat": 42.1136697, "lon": 43.0344264, "tags": {"amenity": "cafe", "name": "Baraka", "name:ka": "\u10d1\u10d0\u10e0\u10d0\u10e5\u10d0"}}, {"type": "node", "id": 4347299689, "lat": 42.1058759, "lon": 43.0523915, "tags": {"amenity": "restaurant", "name": "\u10e1\u10d0\u10d1\u10d0\u10dc\u10d9\u10d4\u10e2\u10dd \u10d3\u10d0\u10e0\u10d1\u10d0\u10d6\u10d8"}}, {"type": "node", "id": 4347303995, "lat": 42.1138551, "lon": 43.2871118, "tags": {"amenity": "restaurant", "name:ru": "\u0427\u0438\u043f\u043e\u0441 \u0425\u0438\u043d\u043a\u0430\u043b\u0438"}}, {"type": "node", "id": 4360210289, "lat": 42.1085328, "lon": 43.0445817, "tags": {"amenity": "restaurant", "name": "\u10e0\u10d4\u10e1\u10e2\u10dd\u10e0\u10d0\u10dc\u10d8 \"\u10ea\u10d0\u10ea\u10ee\u10d5\u10d4\u10d1\u10d8\"", "name:en": "Restaurant \"Tsatskhvebi\"", "name:ka": "\u10e0\u10d4\u10e1\u10e2\u10dd\u10e0\u10d0\u10dc\u10d8 \"\u10ea\u10d0\u10ea\u10ee\u10d5\u10d4\u10d1\u10d8\"", "name:ru": "\u0420\u0435\u0441\u0442\u043e\u0440\u0430\u043d \"\u0426\u0430\u0446\u0445\u0432\u0435\u0431\u0438\""}}, {"type": "node", "id": 4360271089, "lat": 42.1138344, "lon": 43.2874941, "tags": {"amenity": "restaurant", "indoor_seating": "yes", "name": "\u10e0\u10d4\u10e1\u10e2\u10dd\u10e0\u10d0\u10dc\u10d8 \"\u10eb\u10d5\u10d4\u10da\u10d8  \u10e1\u10d0\u10ee\u10da\u10d8\" Restourant \"Old House\" \u0420\u0435\u0441\u0442\u043e\u0440\u0430\u043d \"\"\u0421\u0442\u0430\u0440\u044b\u0439  \u0414\u043e\u043c\"", "name:ka": "\u10e0\u10d4\u10e1\u10e2\u10dd\u10e0\u10d0\u10dc\u10d8 \"\u10eb\u10d5\u10d4\u10da\u10d8  \u10e1\u10d0\u10ee\u10da\u10d8\" Restourant \"Old House\" \u0420\u0435\u0441\u0442\u043e\u0440\u0430\u043d \"\"\u0421\u0442\u0430\u0440\u044b\u0439  \u0414\u043e\u043c\"", "outdoor_seating": "yes"}}, {"type": "node", "id": 4386990389, "lat": 42.117454, "lon": 43.0181645, "tags": {"amenity": "cafe", "name": "\u10d1\u10da\u10d0\u10d6\u10d4\u10e0\u10d9\u10d0\u10e4\u10d4", "name:en": "Blazer", "name:ka": "\u10d1\u10da\u10d0\u10d6\u10d4\u10e0\u10d9\u10d0\u10e4\u10d4"}}, {"type": "node", "id": 4387402291, "lat": 42.100946, "lon": 43.2165563, "tags": {"amenity": "cafe", "name": "\u10d1\u10d0\u10ed\u10d0\u10e2\u10d8\u10d0", "name:ka": "\u10d1\u10d0\u10ed\u10d0\u10e2\u10d8\u10d0"}}, {"type": "node", "id": 4387451589, "lat": 42.1002531, "lon": 43.0713068, "tags": {"amenity": "restaurant"}}, {"type": "node", "id": 4398468496, "lat": 42.107173, "lon": 43.0323565, "tags": {"addr:housenumber": "8", "addr:postcode": "383900", "addr:street": "\u10d0\u10e6\u10db\u10d0\u10e8\u10d4\u10dc\u10d4\u10d1\u10da\u10d8\u10e1 \u10e5\u10e3\u10e9\u10d0 (Aghmashenebeli St)", "amenity": "restaurant", "cuisine": "georgian", "internet_access": "wlan", "microbrewery": "yes", "name:ru": "Buga", "opening_hours": "Mo-Su 09:00-23:00", "operator": "Kako Bugashvili", "phone": "+995599634757", "website": "https://www.facebook.com/pages/Zestafoni-Bugashvilebi/370021863128406"}}, {"type": "node", "id": 4432132789, "lat": 42.1067741, "lon": 43.0181636, "tags": {"amenity": "cafe", "name": "\u10e1\u10d8\u10db\u10dd\u10dc\u10d0\u10e1 \u10d3\u10e3\u10e5\u10d0\u10dc\u10d8", "name:ka": "\u10e1\u10d8\u10db\u10dd\u10dc\u10d0\u10e1 \u10d3\u10e3\u10e5\u10d0\u10dc\u10d8"}}, {"type": "node", "id": 4432133789, "lat": 42.1067192, "lon": 43.0180557, "tags": {"addr:housenumber": "144", "addr:street": "\u10ed\u10d0\u10dc\u10e2\u10e3\u10e0\u10d8\u10d0\u10e1 \u10e5\u10e3\u10e9\u10d0 (Chanturia Str.)", "amenity": "cafe", "cuisine": "georgian", "name": "\u10d0\u10da\u10d8\u10d1\u10d0\u10d1\u10d0\u10e1 \u10d3\u10e3\u10e5\u10d0\u10dc\u10d8", "name:en": "Alibaba Khashi", "name:ka": "\u10d0\u10da\u10d8\u10d1\u10d0\u10d1\u10d0\u10e1 \u10d3\u10e3\u10e5\u10d0\u10dc\u10d8", "name:ru": "\u0410\u043b\u0438\u0431\u0430\u0431\u0430 \u0445\u0430\u0448\u0438", "opening_hours": "Mo-Su 05:00-18:00", "phone": "+995555781888"}}, {"type": "node", "id": 4471304189, "lat": 42.1104365, "lon": 43.0432493, "tags": {"amenity": "cafe", "name:en": "Cafe Fresh"}}, {"type": "node", "id": 4568298089, "lat": 42.1011621, "lon": 42.8163461, "tags": {"amenity": "restaurant", "internet_access": "wlan", "name": "\u10eb\u10d5\u10d4\u10da\u10d8 \u10d3\u10d0\u10e0\u10d1\u10d0\u10d6\u10d8", "name:en": "The Old Palace", "phone": "599271856"}}, {"type": "node", "id": 4716156690, "lat": 42.1960547, "lon": 43.012538, "tags": {"amenity": "bar"}}, {"type": "node", "id": 4839771348, "lat": 42.2469032, "lon": 42.9555295, "tags": {"amenity": "cafe", "cuisine": "georgian", "name": "\u10d9\u10dd\u10d3\u10d0\u10da\u10d0", "name:en": "Woodpecker", "name:ka": "\u10d9\u10dd\u10d3\u10d0\u10da\u10d0", "name:ru": "\u0414\u044f\u0442\u0435\u043b", "operator": "\u0410\u0432\u0442\u043e\u043d\u0434\u0438\u043b", "phone": "+995599327729"}}, {"type": "node", "id": 5266329623, "lat": 42.1097456, "lon": 43.045098, "tags": {"addr:housenumber": "4", "addr:postcode": "2100", "addr:street": "\u10d7\u10d0\u10db\u10d0\u10e0\u10d8\u10e1 \u10e5\u10e3\u10e9\u10d0", "amenity": "cafe", "cuisine": "burger;italian;breakfast;ice_cream;cake;georgian;coffee_shop", "internet_access": "wlan", "name": "Terrasa", "name:ru": "\u0422\u0435\u0440\u0440\u0430\u0441\u0430", "opening_hours": "24/7", "operator": "Phocxverashvili Mixeil"}}, {"type": "node", "id": 5578234321, "lat": 42.1209454, "lon": 42.9621378, "tags": {"amenity": "restaurant", "cuisine": "georgian", "name": "\u10d1\u10e0\u10d4\u10d2\u10dd\u10e3\u10da\u10d0", "name:en": "Bregoula", "opening_hours": "Mo-Su 09:00-00:00", "phone": "+995599156056"}}, {"type": "node", "id": 5744620966, "lat": 42.090172, "lon": 43.1637528}, {"type": "node", "id": 5744620967, "lat": 42.0900741, "lon": 43.1636594}, {"type": "node", "id": 5744620968, "lat": 42.0900429, "lon": 43.1636559}, {"type": "node", "id": 5744620969, "lat": 42.0899874, "lon": 43.1636594}, {"type": "node", "id": 5744620970, "lat": 42.0899112, "lon": 43.163726}, {"type": "node", "id": 5744620971, "lat": 42.0898835, "lon": 43.1638159}, {"type": "node", "id": 5744620972, "lat": 42.0898375, "lon": 43.1638789}, {"type": "node", "id": 5744620973, "lat": 42.0897873, "lon": 43.1641568}, {"type": "node", "id": 5744620974, "lat": 42.089932, "lon": 43.1642654}, {"type": "node", "id": 5744620975, "lat": 42.0900221, "lon": 43.1642257}, {"type": "node", "id": 5744620976, "lat": 42.0900602, "lon": 43.1642093}, {"type": "node", "id": 5766118616, "lat": 42.1806119, "lon": 42.9774534, "tags": {"amenity": "restaurant", "name": "Bavaria"}}, {"type": "node", "id": 5838256885, "lat": 42.1491878, "lon": 42.9633487, "tags": {"amenity": "cafe", "name:en": "313", "name:ru": "313"}}, {"type": "node", "id": 5851142585, "lat": 42.2909752, "lon": 43.2878043, "tags": {"amenity": "cafe"}}, {"type": "node", "id": 5851142586, "lat": 42.2909682, "lon": 43.2879839, "tags": {"amenity": "restaurant", "cuisine": "georgian"}}, {"type": "node", "id": 6265779586, "lat": 42.102999, "lon": 43.225184, "tags": {"amenity": "restaurant", "cuisine": "georgian", "internet_access": "wlan", "name:en": "restorani ANTRE BATONO. supertualet.super parking.", "opening_hours": "Mo-Su 08:00-23:00", "phone": "+995599209090"}}, {"type": "node", "id": 6312169785, "lat": 42.1113748, "lon": 43.0409897, "tags": {"amenity": "cafe", "name": "\u10db\u10d0\u10d8\u10d9\u10dd", "name:en": "Maiko"}}, {"type": "node", "id": 6535740785, "lat": 42.1138822, "lon": 43.0299964, "tags": {"amenity": "cafe", "internet_access": "wlan", "name:ru": "\u0425\u0438\u043d\u043a\u0430\u043b\u0438"}}, {"type": "node", "id": 6609167186, "lat": 42.1072167, "lon": 43.0360894, "tags": {"amenity": "restaurant", "name": "\u10e1\u10d0\u10ee\u10d8\u10dc\u10d9\u10da\u10d4 \"\u10dc\u10d0\u10eb\u10d5\u10d4\u10d1\u10d8\"", "name:ka": "\u10e1\u10d0\u10ee\u10d8\u10dc\u10d9\u10da\u10d4 \"\u10dc\u10d0\u10eb\u10d5\u10d4\u10d1\u10d8\"(\u10d1\u10d4\u10e0\u10d0\u10eb\u10d4\u10d4\u10d1\u10d8\u10e1)"}}, {"type": "node", "id": 6611214985, "lat": 42.106949, "lon": 43.035859, "tags": {"amenity": "cafe", "name": "Baraqa (kofe, xachapuri)"}}, {"type": "node", "id": 6690935486, "lat": 42.112539, "lon": 43.0376998, "tags": {"amenity": "restaurant", "name:en": "Maiko"}}, {"type": "node", "id": 6766678697, "lat": 42.2910242, "lon": 43.2851056, "tags": {"amenity": "cafe"}}, {"type": "node", "id": 6959938685, "lat": 42.2910333, "lon": 43.2853153, "tags": {"amenity": "restaurant", "name": "Cafeish Restaurnt"}}, {"type": "node", "id": 6987549485, "lat": 42.2909569, "lon": 43.2904664, "tags": {"addr:housenumber": "5", "addr:postcode": "5500", "addr:street": "\u10dc\u10d8\u10dc\u10dd\u10e8\u10d5\u10d8\u10da\u10d8\u10e1 \u10e5\u10e3\u10e9\u10d0", "amenity": "restaurant", "cuisine": "georgian", "internet_access": "wlan", "name:en": "Newland Caf\u00e9", "operator": "Newland Hotel"}}, {"type": "node", "id": 7274274586, "lat": 42.1125574, "lon": 43.037623, "tags": {"amenity": "cafe", "name": "\u10e7\u10d0\u10d5\u10d8\u10e1 \u10dd\u10d7\u10d0\u10ee\u10d8"}}, {"type": "node", "id": 7274274587, "lat": 42.1124887, "lon": 43.0377939, "tags": {"amenity": "cafe", "name": "\u10e1\u10ec\u10e0\u10d0\u10e4\u10d8 \u10d9\u10d5\u10d4\u10d1\u10d0 \"\u10e2\u10e3\u10e0\u10d8\u10e1\u10e2\u10d8\""}}, {"type": "node", "id": 7274274588, "lat": 42.1125605, "lon": 43.037437, "tags": {"amenity": "cafe", "name": "\u10d7\u10d0\u10dc \u10ec\u10d0\u10d8\u10e6\u10d4"}}, {"type": "node", "id": 7806443427, "lat": 42.1457721, "lon": 42.9818685, "tags": {"addr:city": "\u10d0\u10e0\u10d2\u10d5\u10d4\u10d7\u10d0", "amenity": "restaurant", "name": "\u10da\u10d8\u10d0 \u10d3\u10d4\u10d8\u10d3\u10d0", "name:en": "Lia Deida", "name:ka": "\u10da\u10d8\u10d0 \u10d3\u10d4\u10d8\u10d3\u10d0"}}, {"type": "node", "id": 9576832917, "lat": 42.0673892, "lon": 42.825405, "tags": {"amenity": "cafe"}}, {"type": "node", "id": 10773963701, "lat": 42.3064739, "lon": 42.7399093}, {"type": "node", "id": 10773963702, "lat": 42.3064064, "lon": 42.7397886}, {"type": "node", "id": 10773963703, "lat": 42.3062775, "lon": 42.739751}, {"type": "node", "id": 10773963704, "lat": 42.3061843, "lon": 42.7397725}, {"type": "node", "id": 10773968205, "lat": 42.3060494, "lon": 42.7397993}, {"type": "node", "id": 10773968206, "lat": 42.3059105, "lon": 42.7398288}, {"type": "node", "id": 10773968207, "lat": 42.3057994, "lon": 42.7398637}, {"type": "node", "id": 10773968208, "lat": 42.3058351, "lon": 42.7401614}, {"type": "node", "id": 10773968209, "lat": 42.3059839, "lon": 42.740207}, {"type": "node", "id": 10773968210, "lat": 42.3061843, "lon": 42.7401748}, {"type": "node", "id": 10773968211, "lat": 42.3064203, "lon": 42.7401373}, {"type": "node", "id": 10773968212, "lat": 42.3064937, "lon": 42.74003}, {"type": "node", "id": 10939747205, "lat": 42.1645063, "lon": 42.9404758, "tags": {"amenity": "cafe"}}, {"type": "node", "id": 10939748005, "lat": 42.1644477, "lon": 42.9405549, "tags": {"amenity": "cafe"}}, {"type": "node", "id": 11003418350, "lat": 42.2662144, "lon": 42.7302612}, {"type": "node", "id": 11003418351, "lat": 42.2660834, "lon": 42.7301593}, {"type": "node", "id": 11003418352, "lat": 42.2661486, "lon": 42.7300063}, {"type": "node", "id": 11003418353, "lat": 42.2662796, "lon": 42.7301082}, {"type": "node", "id": 11007808126, "lat": 42.2909118, "lon": 43.2853622, "tags": {"amenity": "cafe", "cuisine": "georgian", "name": "Cafe de Paris", "outdoor_seating": "no"}}, {"type": "node", "id": 11049034524, "lat": 42.2911459, "lon": 43.2882789, "tags": {"amenity": "cafe", "check_date": "2023-07-16", "name:ka": "\u1c9c\u10d8\u10dc\u10d0"}}, {"type": "node", "id": 11429274776, "lat": 42.0662311, "lon": 42.8283748}, {"type": "node", "id": 11429274777, "lat": 42.0661065, "lon": 42.8285498}, {"type": "node", "id": 11429274778, "lat": 42.066197, "lon": 42.8285774}, {"type": "node", "id": 11429274779, "lat": 42.0661406, "lon": 42.8283472}, {"type": "node", "id": 11479155769, "lat": 42.1111605, "lon": 43.3021543, "tags": {"addr:street": "\u10d7\u10d1\u10d8\u10da\u10d8\u10e1\u10d8-\u10e1\u10d4\u10dc\u10d0\u10d9\u10d8-\u10da\u10d4\u10e1\u10d4\u10da\u10d8\u10eb\u10d4", "amenity": "restaurant", "name": "\u10f0\u10d1 \u10e0\u10d8\u10d9\u10dd\u10d7\u10d8 hb rikoti", "name:en": "HB Rikoti", "opening_hours": "Mo-Su 09:00-22:00", "phone": "+995 511 30 13 31"}}, {"type": "way", "id": 263461161, "nodes": [2690807611, 2690807603, 2690807571, 2690807584, 2690807611], "tags": {"amenity": "restaurant", "building": "yes", "name": "\u10e1\u10d8\u10db\u10dd\u10dc\u10d4\u10d7\u10d8", "name:en": "Simoneti", "tourism": "hotel"}}, {"type": "way", "id": 420861896, "nodes": [4207616643, 4207616644, 4207616645, 4207616646, 4207616647, 4207616648, 4207616649, 4207616650, 4207616643], "tags": {"amenity": "cafe", "building": "yes", "name": "\u0421\u0442\u043e\u043b\u043e\u0432\u0430\u044f"}}, {"type": "way", "id": 605752774, "nodes": [5744620966, 5744620967, 5744620968, 5744620969, 5744620970, 5744620971, 5744620972, 5744620973, 5744620974, 5744620975, 5744620976, 5744620966], "tags": {"amenity": "restaurant", "cuisine": "regional;kebab", "indoor_seating": "yes", "name": "\u10db\u10ec\u10d5\u10d0\u10d3\u10d8\u10d0\u10e3\u10e0\u10d8 \u10d8\u10db\u10d4\u10e0\u10d4\u10d7\u10e8\u10d8", "name:en": "Mtsvadiauri Imeretshi", "name:ru": "\u041c\u0446\u0432\u0430\u0434\u0438\u0430\u0443\u0440\u0438 \u0432 \u0418\u043c\u0435\u0440\u0435\u0442\u0438", "outdoor_seating": "yes"}}, {"type": "way", "id": 1158515551, "nodes": [10773963701, 10773963702, 10773963703, 10773963704, 10773968205, 10773968206, 10773968207, 10773968208, 10773968209, 10773968210, 10773968211, 10773968212, 10773963701], "tags": {"amenity": "restaurant", "cuisine": "regional", "name": "\u10e0\u10d4\u10e1\u10e2\u10dd\u10e0\u10d0\u10dc\u10d8 \"\u10e1\u10dd\u10e0\u10db\u10dd\u10dc\u10d8\""}}, {"type": "way", "id": 1184678991, "nodes": [11003418353, 11003418350, 11003418351, 11003418352, 11003418353], "tags": {"amenity": "restaurant", "building": "yes", "name": "\u10d5\u10d4\u10e0\u10d0\u10dc\u10d3\u10d0", "name:en": "Veranda", "name:ka": "\u10d5\u10d4\u10e0\u10d0\u10dc\u10d3\u10d0"}}, {"type": "way", "id": 1232213048, "nodes": [11429274777, 11429274779, 11429274776, 11429274778, 11429274777], "tags": {"amenity": "restaurant", "name": "\u10dc\u10d0\u10eb\u10d5\u10d4\u10d1\u10d8", "name:en": "Nadzvebi", "wheelchair": "limited"}}]}